{
    "resultdata":"1",
    "errordata":"注册成功",
    "ResData": {
      "id": 10,
      "name": "巴山有机农家自产香菇",
      "price": 90,
      "isCollect": false,
      "imgs": [
        {
          "url": "javascript:",
          "img": "/src/assets/images/goods_img.png",
          "title": "巴山有机农家自产香菇900g",
          "fallbackImg": "/src/assets/images/default.gif"
        },
        {
          "url": "javascript:",
          "img": "/src/assets/images/goods_img.png",
          "title": "巴山有机农家自产香菇900g",
          "fallbackImg": "/src/assets/images/default.gif"
        },
        {
          "url": "javascript:",
          "img": "/src/assets/images/goods_img.png",
          "title": "巴山有机农家自产香菇900g",
          "fallbackImg": "/src/assets/images/default.gif"
        }
      ]
    }
}